spssio/__init__.py
spssio/libspss/document/Input-Output Module.pdf
spssio/libspss/include/spssdio.h
spssio/libspss/include/spssdiocodes.h
spssio/libspss/lin64/libgsk8iccs_64.so
spssio/libspss/lin64/libicudata.so.61
spssio/libspss/lin64/libicudata.so.61.2
spssio/libspss/lin64/libicui18n.so.61
spssio/libspss/lin64/libicui18n.so.61.2
spssio/libspss/lin64/libicuuc.so.61
spssio/libspss/lin64/libicuuc.so.61.2
spssio/libspss/lin64/libspssdio.so.1
spssio/libspss/lin64/libspssjdio.so.1
spssio/libspss/lin64/libzlib1213spss.so
spssio/libspss/macos/libgsk8iccs.dylib
spssio/libspss/macos/libicudata.61.2.dylib
spssio/libspss/macos/libicui18n.61.2.dylib
spssio/libspss/macos/libicuuc.61.2.dylib
spssio/libspss/macos/libspssdio.dylib
spssio/libspss/macos/libspssjdio.dylib
spssio/libspss/macos/libzlib1213spss.dylib
spssio/libspss/win64/gsk8iccs_64.dll
spssio/libspss/win64/icudt61.dll
spssio/libspss/win64/icuin61.dll
spssio/libspss/win64/icuuc61.dll
spssio/libspss/win64/msvcp120.dll
spssio/libspss/win64/msvcr120.dll
spssio/libspss/win64/spssdio.vb
spssio/libspss/win64/spssio64.dll
spssio/libspss/win64/spssio64.lib
spssio/libspss/win64/spssjdio.dll
spssio/libspss/win64/vccorlib120.dll
spssio/libspss/win64/zlib1213spss.dll
spssio/py.typed
spssio-0.2.5.dist-info/WHEEL
spssio-0.2.5.dist-info/METADATA
spssio-0.2.5.dist-info/RECORD
