Metadata-Version: 2.3
Name: spssio
Version: 0.2.5
Summary: Pythonic, fast access to SPSS files
Author: Jose Tiago Macara Coutinho
Author-email: Jose Tiago Macara Coutinho <coutinhotiago@gmail.com>
Requires-Dist: numpy>=1.8
Requires-Python: >=3.11
